amqp_aio/__init__.py
amqp_aio-0.0.1.dist-info/LICENSE
amqp_aio-0.0.1.dist-info/METADATA
amqp_aio-0.0.1.dist-info/WHEEL
amqp_aio-0.0.1.dist-info/top_level.txt
amqp_aio-0.0.1.dist-info/RECORD
