Metadata-Version: 2.1
Name: amqp-aio
Version: 0.0.1
Summary: Async AMQP Library
Home-page: https://github.com/Mendes11/amqp-aio
Author: Rafael Mendes Pacini Bachiega
Author-email: rafaelmpb11@hotmail.com
License: UNKNOWN
Platform: UNKNOWN
Classifier: Intended Audience :: Developers
Classifier: Operating System :: OS Independent
Classifier: Programming Language :: Python :: 3 :: Only
Classifier: Programming Language :: Python :: 3.6
Classifier: Programming Language :: Python :: 3.7
Classifier: Programming Language :: Python :: 3.8
Classifier: Programming Language :: Python :: 3.9
License-File: LICENSE
Requires-Dist: aiormq (<6)
